README.md
setup.py
hanyutools.egg-info/PKG-INFO
hanyutools.egg-info/SOURCES.txt
hanyutools.egg-info/dependency_links.txt
hanyutools.egg-info/top_level.txt
hytools/__init__.py
hytools/utilitieshy.py