Metadata-Version: 1.0
Name: hanyutools
Version: 0.1.4
Summary:  tool edited by hanyu
Home-page: https://github.com/DruidHanyu
Author: Hanyu
Author-email: zhanghanyu94@bupt.edu.cn
License: Hanyu Licence
Keywords: pip,hanyutools,hanyu
Platform: any
